molscraper/__init__.py
molscraper/cli.py
molscraper/scraper.py
molscraper/pyarmor_runtime_000000/__init__.py
molscraper/pyarmor_runtime_000000/pyarmor_runtime.so
molscraper_tool-1.0.0.dist-info/licenses/LICENSE
pyarmor_runtime_000000/__init__.py
molscraper_tool-1.0.0.dist-info/METADATA
molscraper_tool-1.0.0.dist-info/WHEEL
molscraper_tool-1.0.0.dist-info/entry_points.txt
molscraper_tool-1.0.0.dist-info/top_level.txt
molscraper_tool-1.0.0.dist-info/RECORD
