Metadata-Version: 2.4
Name: molscraper-tool
Version: 1.0.0
Summary: Chemical data extraction tool for researchers and chemists
Author: Xhuliano Brace, Timothy Chia
Author-email: x@rhizome-research.com, tim@rhizome-research.com
Project-URL: Documentation, https://github.com/xhuliano/molscraper#readme
Project-URL: Bug Reports, https://github.com/xhuliano/molscraper/issues
Project-URL: Source, https://github.com/xhuliano/molscraper
Keywords: chemistry,pubchem,chemical-data,molecules,research,cas-numbers,chemical-properties,data-extraction,scientific-computing,cheminformatics
Classifier: Development Status :: 4 - Beta
Classifier: Intended Audience :: Science/Research
Classifier: Intended Audience :: Developers
Classifier: Topic :: Scientific/Engineering :: Chemistry
Classifier: Topic :: Scientific/Engineering :: Information Analysis
Classifier: License :: OSI Approved :: MIT License
Classifier: Programming Language :: Python :: 3
Classifier: Programming Language :: Python :: 3.8
Classifier: Programming Language :: Python :: 3.9
Classifier: Programming Language :: Python :: 3.10
Classifier: Programming Language :: Python :: 3.11
Classifier: Programming Language :: Python :: 3.12
Classifier: Operating System :: OS Independent
Requires-Python: >=3.8
License-File: LICENSE
Requires-Dist: pandas>=1.5.0
Requires-Dist: requests>=2.28.0
Requires-Dist: openpyxl>=3.0.0
Dynamic: author
Dynamic: author-email
Dynamic: classifier
Dynamic: description
Dynamic: description-content-type
Dynamic: keywords
Dynamic: license-file
Dynamic: project-url
Dynamic: requires-dist
Dynamic: requires-python
Dynamic: summary
